README.md
setup.py
bin/seread
seread/sng.py
seread/version.py
seread.egg-info/PKG-INFO
seread.egg-info/SOURCES.txt
seread.egg-info/dependency_links.txt
seread.egg-info/requires.txt
seread.egg-info/top_level.txt