Metadata-Version: 2.1
Name: seread
Version: 0.2.31
Summary: Script to read serial port and store to file/influxdb
Home-page: http://gitlab.com/jaromrax/seread
Author: jaromrax
Author-email: jaromrax@gmail.com
License: GPL2
Platform: UNKNOWN
